huaweicloudsdknlp/__init__.py
huaweicloudsdknlp/v2/__init__.py
huaweicloudsdknlp/v2/nlp_async_client.py
huaweicloudsdknlp/v2/nlp_client.py
huaweicloudsdknlp/v2/model/__init__.py
huaweicloudsdknlp/v2/model/aspect_advance_opinion.py
huaweicloudsdknlp/v2/model/aspect_opinion.py
huaweicloudsdknlp/v2/model/aspect_sentiment_advance_request.py
huaweicloudsdknlp/v2/model/aspect_sentiment_request.py
huaweicloudsdknlp/v2/model/classification_req.py
huaweicloudsdknlp/v2/model/classification_result.py
huaweicloudsdknlp/v2/model/constituency_parser_req.py
huaweicloudsdknlp/v2/model/create_poem.py
huaweicloudsdknlp/v2/model/dependency_parser_request.py
huaweicloudsdknlp/v2/model/dependency_parser_word.py
huaweicloudsdknlp/v2/model/document_classification_req.py
huaweicloudsdknlp/v2/model/domain_named_entity.py
huaweicloudsdknlp/v2/model/domain_sentiment_req.py
huaweicloudsdknlp/v2/model/entity_sentiment_req.py
huaweicloudsdknlp/v2/model/event_extraction_response_item.py
huaweicloudsdknlp/v2/model/event_extraction_response_item_argument.py
huaweicloudsdknlp/v2/model/file_translation_req.py
huaweicloudsdknlp/v2/model/hw_cloud_sentiment_req.py
huaweicloudsdknlp/v2/model/hw_cloud_sentiment_resp.py
huaweicloudsdknlp/v2/model/intent_req.py
huaweicloudsdknlp/v2/model/intent_result.py
huaweicloudsdknlp/v2/model/keyword_extract_req.py
huaweicloudsdknlp/v2/model/language_detection_req.py
huaweicloudsdknlp/v2/model/linked_entity.py
huaweicloudsdknlp/v2/model/named_entity.py
huaweicloudsdknlp/v2/model/ner_request.py
huaweicloudsdknlp/v2/model/post_domain_ner_request.py
huaweicloudsdknlp/v2/model/post_entity_linking_request.py
huaweicloudsdknlp/v2/model/post_event_extraction_req.py
huaweicloudsdknlp/v2/model/post_multi_gained_segment_response_item.py
huaweicloudsdknlp/v2/model/post_multi_gained_segment_response_item_copy.py
huaweicloudsdknlp/v2/model/post_multi_grained_segment_req.py
huaweicloudsdknlp/v2/model/post_sentence_embedding_req.py
huaweicloudsdknlp-3.1.184.dist-info/METADATA
huaweicloudsdknlp-3.1.184.dist-info/WHEEL
huaweicloudsdknlp-3.1.184.dist-info/licenses/LICENSE
huaweicloudsdknlp-3.1.184.dist-info/RECORD
